{
    "Header": {

        "logo_banner": "img/logo_banner.png",
        "title": "titulo",
        "paragraph": "Lorem ipsum dolor sit amet, consectetur adipiscing elit. Duis sed dapibus leo nec ornare diam sed commodo nibh ante facilisis bibendum."

    },
    "About": {
        "paragraph1": "Chile6Miles, es un proyecto deportivo que busca escalar todas las cumbres de mas de 6.000 msnm de los Andes Chilenos.  Se trata de 37 montañas que cumplen esta característica, que se encuentran distribuidas desde la Región de Arica y Parinacota, hasta la Región Metropolitana. Dentro de este grupo de montañas, existen algunas icónicas, como el Volcán Ojos del Salado que con sus 6.893 msnm, se alza como el volcán activo más grande del mundo y la segunda mayor altura de américa, o el Cerro Marmolejo, que con sus 6.108 msnm tiene la categoría de ser el 6mil más austral del mundo.",
        "paragraph2": "Dado que no existen registros de equipos chilenos que hayan realizado esta hazaña, buscamos ser los primeros nacionales en lograrlo, detallando rutas e información útil, documentar el cambio climático en la cordillera de los Andes Chilenos y generar material audiovisual actualizado.",
        "paragraph3": "Siendo Chile un país de montaña y con una cultura montañista creciente, buscamos con este proyecto dar a conocer las altas cumbres Chilenas a la comunidad nacional e internacional, y ser una motivación para experimentar la montaña y su práctica segura.",
        "invitation": "Los invitamos a seguir nuestra aventura.",
        "info": "Persigo la felicidad. Y la montaña responde a mi búsqueda.",
        "author": "[Chantal Maudit]",
        "image": "img/project.jpg"
        
    },
    "Services": [
        {
            "icon": "fa fa-wordpress",
            "name": "Andesgear",
            "src": "img/logo_andesgear.png",
            "page": "https://www.andesgear.cl/"
        },
        {
            "icon": "fa fa-wordpress",
            "name": "Nespra Smart Devices",
            "src": "img/logo_nespra.png",
            "page": "https://www.nespra.net/"
        },
        {
            "icon": "fa fa-wordpress",
            "name": "Ilustre Municipalidad de Graneros",
            "src": "img/logo_muni.png",
            "page": "https://www.municipalidadgraneros.cl/"
        },
        {
            "icon": "fa fa-wordpress",
            "name": "Ulmo Power Honey",
            "src": "img/logo_power_honey.png",
            "page": "https://powerhoney.cl/"
        },
        {
            "icon": "fa fa-cart-arrow-down",
            "name": "NUMEC Ingeniería y Montaje",
            "src": "img/logo_numerec.png",
            "page": "https://www.numec.cl/"
        },
        {
            "icon": "fa fa-cloud-download",
            "name": "NAC Ingeniería",
            "src": "img/nac_logo.png",
            "page": "https://www.nacingenieria.com/"
        }
    ],

    "Galley": [{
        "src": "img/portafolio/1.jpg"
    },
    {
        "src": "img/portafolio/2.jpg"
    },
    {
        "src": "img/portafolio/3.jpg"
    }
],
    "Testimonials": [{
            "img": "img/testimonials/01.jpg",
            "text": "\"Lorem ipsum dolor sit amet, consectetur adipiscing elit. Duis sed dapibus leo nec ornare diam sedasd commodo nibh ante facilisis bibendum dolor feugiat at.\"",
            "name": "John Doe"
        },
        {
            "img": "img/testimonials/02.jpg",
            "text": "\"Lorem ipsum dolor sit amet, consectetur adipiscing elit. Duis sed dapibus leo nec ornare diam sedasd commodo nibh ante facilisis bibendum dolor feugiat at.\"",
            "name": "Johnathan Doe"
        },
        {
            "img": "img/testimonials/03.jpg",
            "text": "\"Lorem ipsum dolor sit amet, consectetur adipiscing elit. Duis sed dapibus leo nec ornare diam sedasd commodo nibh ante facilisis bibendum dolor feugiat at.\"",
            "name": "John Doe"
        },
        {
            "img": "img/testimonials/04.jpg",
            "text": "\"Lorem ipsum dolor sit amet, consectetur adipiscing elit. Duis sed dapibus leo nec ornare diam sedasd commodo nibh ante facilisis bibendum dolor feugiat at.\"",
            "name": "Johnathan Doe"
        },
        {
            "img": "img/testimonials/05.jpg",
            "text": "\"Lorem ipsum dolor sit amet, consectetur adipiscing elit. Duis sed dapibus leo nec ornare diam sedasd commodo nibh ante facilisis bibendum dolor feugiat at.\"",
            "name": "John Doe"
        },
        {
            "img": "img/testimonials/06.jpg",
            "text": "\"Lorem ipsum dolor sit amet, consectetur adipiscing elit. Duis sed dapibus leo nec ornare diam sedasd commodo nibh ante facilisis bibendum dolor feugiat at.\"",
            "name": "Johnathan Doe"
        }
    ],
    "Team": {
        "title": {
            "team1" : "Somos un equipo joven y entusiasta, apasionado de las actividades de montaña y la aventura, con cumbres como el Aconcagua, Ojos del Salado, Volcán Acotango, Volcán Guallatiri y gran parte de Los Andes Centrales, hasta travesías desde Patagonia al Norte de Chile.",
            "team2" : "Nuestra aspiración es difundir las actividades de montaña, su práctica en forma segura y ser un aporte a la cultura de montaña de Chile."
        },
        "members": [{
            "img": "img/team/nicolas.jpg",
            "name": "Nicolás Núñez S.",
            "job": ""
        },
        {
            "img": "img/team/hernan.jpg",
            "name": "Hernán Núñez Cristi",
            "job": ""
        }
    ]
    },
    "Contact": {
        "address": "Guardia Vieja 181, Of 506. Providencia, Chile.",
        "phone": "(+569) 90933114",
        "email": "info@chile6miles.cl",
        "instagram": "https://www.instagram.com/chile6miles/",
        "twitter": "twitter.com",
        "youtube": "youtube.com"
    },
    "Features": [{
            "id" : "1",
            "icon": "fa-mountain",
            "title": "Arica y Parinacota",
            "text": "5 Volcanes",
            "img": "img/places/climb.png",
            "detail" : [
                {
                    "name" : "Volcán Parinacota",
                    "elevation" : "6,348 m",
                    "first": "1928. Joseph Prem (AT) y CarlosTerán (BO), 12 de diciembre.",
                    "type": "Estratovolcán",
                    "route": "Nieve-roca",
                    "andeshandbook": "https://www.andeshandbook.org/montanismo/cerro/15/Parinacota"
                },
                {
                    "name" : "Volcán Guallatiri",
                    "elevation" : "6,071 m",
                    "first": "1926. Friedrich Ahlfeld (DE)",
                    "type": "Estratovolcán",
                    "route": "-",
                    "andeshandbook": "https://www.andeshandbook.org/montanismo/cerro/14/Guallatiri"
                },
                {
                    "name" : "Volcán Acotango",
                    "elevation" : "6,348 m",
                    "first": "1928",
                    "type": "Estratovolcán",
                    "route": "Nieve-roca",
                    "andeshandbook": "https://www.andeshandbook.org/montanismo/cerro/15/Parinacota"
                }
        ]
        },
        {
            "id" : "2",
            "icon": "fa fa-comments-o",
            "title": "Antofagasta",
            "text": "9 Volcanes",
            "img": "img/places/climb.png"
        },
        {
            "id" : "3",
            "icon": "fa-group",
            "title": "Atacama",
            "img": "img/places/climb.png",
            "text": "3 Cerros, 8 Volcanes, 5 Nevados"
        },
        {
            "id" : "4",
            "icon": "fa-magic",
            "title": "Coquimbo",
            "text": "1 Cerro, 1 Nevado",
            "img": "img/places/climb.png"
        },
        {
            "id" : "5",
            "icon": "fa fa-magic",
            "title": "Metropolitana",
            "text": "1 Cerro, 2 Nevados, 2 Volcanes",
            "img": "img/places/climb.png"
        }
    ]
}